mahalanobis/__init__.py
mahalanobis-1.0.dist-info/LICENSE.txt
mahalanobis-1.0.dist-info/METADATA
mahalanobis-1.0.dist-info/WHEEL
mahalanobis-1.0.dist-info/top_level.txt
mahalanobis-1.0.dist-info/RECORD
