Metadata-Version: 2.1
Name: mahalanobis
Version: 1.0
Summary: Package for performing calculations of Mahalanobis distances
Home-page: https://github.com/mosegui/mahalanobis
Author: Daniel Moseguí González
Author-email: d.mosegui@gmail.com
License: UNKNOWN
Platform: UNKNOWN
Classifier: Programming Language :: Python :: 3
Classifier: License :: OSI Approved :: MIT License
Classifier: Operating System :: OS Independent
Requires-Python: >=3.6
